{
  "stackName": "amplify-lightshow-dev-101954",
  "props": {
    "templateFile": "root-stack-template.json",
    "parameters": {
      "AuthRoleName": "amplify-lightshow-dev-101954-authRole",
      "UnauthRoleName": "amplify-lightshow-dev-101954-unauthRole",
      "DeploymentBucketName": "amplify-lightshow-dev-101954-deployment"
    },
    "preserveLogicalIds": true,
    "loadNestedStacks": {
      "APIGatewayAuthStack": {
        "templateFile": "auth/APIGatewayAuthStack.json",
        "parameters": {
          "env": "dev"
        },
        "preserveLogicalIds": true,
        "loadNestedStacks": {}
      },
      "apilightshowapi": {
        "templateFile": "api/lightshowapi/lightshowapi-cloudformation-template.json",
        "parameters": {
          "env": "dev"
        },
        "preserveLogicalIds": true,
        "loadNestedStacks": {}
      },
      "authlightshowd4e81427": {
        "templateFile": "auth/lightshowd4e81427/lightshowd4e81427-cloudformation-template.json",
        "parameters": {
          "identityPoolName": "lightshowd4e81427_identitypool_d4e81427",
          "allowUnauthenticatedIdentities": false,
          "resourceNameTruncated": "lightsd4e81427",
          "userPoolName": "lightshowd4e81427_userpool_d4e81427",
          "autoVerifiedAttributes": [
            "email"
          ],
          "mfaConfiguration": "OFF",
          "mfaTypes": [
            "SMS Text Message"
          ],
          "smsAuthenticationMessage": "Your authentication code is {####}",
          "smsVerificationMessage": "Your verification code is {####}",
          "emailVerificationSubject": "Your verification code",
          "emailVerificationMessage": "Your verification code is {####}",
          "defaultPasswordPolicy": false,
          "passwordPolicyMinLength": 8,
          "passwordPolicyCharacters": [],
          "requiredAttributes": [
            "email"
          ],
          "aliasAttributes": [],
          "userpoolClientGenerateSecret": false,
          "userpoolClientRefreshTokenValidity": 30,
          "userpoolClientWriteAttributes": [
            "email"
          ],
          "userpoolClientReadAttributes": [
            "email"
          ],
          "userpoolClientLambdaRole": "lightsd4e81427_userpoolclient_lambda_role",
          "userpoolClientSetAttributes": false,
          "sharedId": "d4e81427",
          "resourceName": "lightshowd4e81427",
          "authSelections": "identityPoolAndUserPool",
          "useDefault": "default",
          "userPoolGroupList": [],
          "serviceName": "Cognito",
          "usernameCaseSensitive": false,
          "useEnabledMfas": true,
          "breakCircularDependency": true,
          "dependsOn": [],
          "env": "dev"
        },
        "preserveLogicalIds": true,
        "loadNestedStacks": {}
      },
      "functionlightshowfunc": {
        "templateFile": "function/lightshowfunc/lightshowfunc-cloudformation-template.json",
        "parameters": {
          "lightId": "d073d55a3d57",
          "secretsPathAmplifyAppId": "d1yd7xpdewj1i5",
          "deploymentBucketName": "amplify-lightshow-dev-101954-deployment",
          "s3Key": "amplify-builds/lightshowfunc-4b2b4962385530724b45-build.zip",
          "env": "dev"
        },
        "preserveLogicalIds": true,
        "loadNestedStacks": {}
      }
    }
  }
}